repository/__init__.py
repository/repository.py
fastapi_repository_sstormss_0.0.2-0.0.2.dist-info/LICENSE
fastapi_repository_sstormss_0.0.2-0.0.2.dist-info/METADATA
fastapi_repository_sstormss_0.0.2-0.0.2.dist-info/WHEEL
fastapi_repository_sstormss_0.0.2-0.0.2.dist-info/top_level.txt
fastapi_repository_sstormss_0.0.2-0.0.2.dist-info/RECORD
